[
    {
        "id": 100,
        "state": "payment",
        "name": "Nguyen 100 Thanh",
        "quantity": 200,
        "dateOrder": "18.06.2019",
        "total": 4700000,
        "level": 0
    },
    {
        "id": 101,
        "state": "payment",
        "name": "Nguyen 101 Thanh",
        "quantity": 202,
        "dateOrder": "18.06.2019",
        "total": 4747000,
        "level": 1
    },
    {
        "id": 102,
        "state": "payment",
        "name": "Nguyen 102 Thanh",
        "quantity": 204,
        "dateOrder": "18.06.2019",
        "total": 4794000,
        "level": 1
    },
    {
        "id": 103,
        "state": "payment",
        "name": "Nguyen 103 Thanh",
        "quantity": 206,
        "dateOrder": "18.06.2019",
        "total": 4841000,
        "level": 0
    },
    {
        "id": 104,
        "state": "payment",
        "name": "Nguyen 104 Thanh",
        "quantity": 208,
        "dateOrder": "18.06.2019",
        "total": 4888000,
        "level": 0
    },
    {
        "id": 105,
        "state": "payment",
        "name": "Nguyen 105 Thanh",
        "quantity": 210,
        "dateOrder": "18.06.2019",
        "total": 4935000,
        "level": 1
    },
    {
        "id": 106,
        "state": "payment",
        "name": "Nguyen 106 Thanh",
        "quantity": 212,
        "dateOrder": "18.06.2019",
        "total": 4982000,
        "level": 0
    },
    {
        "id": 107,
        "state": "payment",
        "name": "Nguyen 107 Thanh",
        "quantity": 214,
        "dateOrder": "18.06.2019",
        "total": 5029000,
        "level": 0
    },
    {
        "id": 108,
        "state": "payment",
        "name": "Nguyen 108 Thanh",
        "quantity": 216,
        "dateOrder": "18.06.2019",
        "total": 5076000,
        "level": 0
    },
    {
        "id": 109,
        "state": "payment",
        "name": "Nguyen 109 Thanh",
        "quantity": 218,
        "dateOrder": "18.06.2019",
        "total": 5123000,
        "level": 1
    },
    {
        "id": 110,
        "state": "payment",
        "name": "Nguyen 110 Thanh",
        "quantity": 220,
        "dateOrder": "18.06.2019",
        "total": 5170000,
        "level": 1
    },
    {
        "id": 111,
        "state": "payment",
        "name": "Nguyen 111 Thanh",
        "quantity": 222,
        "dateOrder": "18.06.2019",
        "total": 5217000,
        "level": 0
    },
    {
        "id": 112,
        "state": "payment",
        "name": "Nguyen 112 Thanh",
        "quantity": 224,
        "dateOrder": "18.06.2019",
        "total": 5264000,
        "level": 1
    },
    {
        "id": 113,
        "state": "payment",
        "name": "Nguyen 113 Thanh",
        "quantity": 226,
        "dateOrder": "18.06.2019",
        "total": 5311000,
        "level": 1
    },
    {
        "id": 114,
        "state": "payment",
        "name": "Nguyen 114 Thanh",
        "quantity": 228,
        "dateOrder": "18.06.2019",
        "total": 5358000,
        "level": 1
    },
    {
        "id": 115,
        "state": "payment",
        "name": "Nguyen 115 Thanh",
        "quantity": 230,
        "dateOrder": "18.06.2019",
        "total": 5405000,
        "level": 1
    },
    {
        "id": 116,
        "state": "payment",
        "name": "Nguyen 116 Thanh",
        "quantity": 232,
        "dateOrder": "18.06.2019",
        "total": 5452000,
        "level": 0
    },
    {
        "id": 117,
        "state": "payment",
        "name": "Nguyen 117 Thanh",
        "quantity": 234,
        "dateOrder": "18.06.2019",
        "total": 5499000,
        "level": 1
    },
    {
        "id": 118,
        "state": "payment",
        "name": "Nguyen 118 Thanh",
        "quantity": 236,
        "dateOrder": "18.06.2019",
        "total": 5546000,
        "level": 0
    },
    {
        "id": 119,
        "state": "payment",
        "name": "Nguyen 119 Thanh",
        "quantity": 238,
        "dateOrder": "18.06.2019",
        "total": 5593000,
        "level": 1
    },
    {
        "id": 120,
        "state": "payment",
        "name": "Nguyen 120 Thanh",
        "quantity": 240,
        "dateOrder": "18.06.2019",
        "total": 5640000,
        "level": 1
    },
    {
        "id": 121,
        "state": "payment",
        "name": "Nguyen 121 Thanh",
        "quantity": 242,
        "dateOrder": "18.06.2019",
        "total": 5687000,
        "level": 1
    },
    {
        "id": 122,
        "state": "payment",
        "name": "Nguyen 122 Thanh",
        "quantity": 244,
        "dateOrder": "18.06.2019",
        "total": 5734000,
        "level": 0
    },
    {
        "id": 123,
        "state": "payment",
        "name": "Nguyen 123 Thanh",
        "quantity": 246,
        "dateOrder": "18.06.2019",
        "total": 5781000,
        "level": 0
    },
    {
        "id": 124,
        "state": "payment",
        "name": "Nguyen 124 Thanh",
        "quantity": 248,
        "dateOrder": "18.06.2019",
        "total": 5828000,
        "level": 1
    },
    {
        "id": 125,
        "state": "payment",
        "name": "Nguyen 125 Thanh",
        "quantity": 250,
        "dateOrder": "18.06.2019",
        "total": 5875000,
        "level": 1
    },
    {
        "id": 126,
        "state": "payment",
        "name": "Nguyen 126 Thanh",
        "quantity": 252,
        "dateOrder": "18.06.2019",
        "total": 5922000,
        "level": 0
    },
    {
        "id": 127,
        "state": "payment",
        "name": "Nguyen 127 Thanh",
        "quantity": 254,
        "dateOrder": "18.06.2019",
        "total": 5969000,
        "level": 1
    },
    {
        "id": 128,
        "state": "payment",
        "name": "Nguyen 128 Thanh",
        "quantity": 256,
        "dateOrder": "18.06.2019",
        "total": 6016000,
        "level": 0
    },
    {
        "id": 129,
        "state": "payment",
        "name": "Nguyen 129 Thanh",
        "quantity": 258,
        "dateOrder": "18.06.2019",
        "total": 6063000,
        "level": 0
    },
    {
        "id": 130,
        "state": "payment",
        "name": "Nguyen 130 Thanh",
        "quantity": 260,
        "dateOrder": "18.06.2019",
        "total": 6110000,
        "level": 0
    },
    {
        "id": 131,
        "state": "payment",
        "name": "Nguyen 131 Thanh",
        "quantity": 262,
        "dateOrder": "18.06.2019",
        "total": 6157000,
        "level": 0
    },
    {
        "id": 132,
        "state": "payment",
        "name": "Nguyen 132 Thanh",
        "quantity": 264,
        "dateOrder": "18.06.2019",
        "total": 6204000,
        "level": 1
    },
    {
        "id": 133,
        "state": "payment",
        "name": "Nguyen 133 Thanh",
        "quantity": 266,
        "dateOrder": "18.06.2019",
        "total": 6251000,
        "level": 0
    },
    {
        "id": 134,
        "state": "payment",
        "name": "Nguyen 134 Thanh",
        "quantity": 268,
        "dateOrder": "18.06.2019",
        "total": 6298000,
        "level": 1
    },
    {
        "id": 135,
        "state": "payment",
        "name": "Nguyen 135 Thanh",
        "quantity": 270,
        "dateOrder": "18.06.2019",
        "total": 6345000,
        "level": 1
    },
    {
        "id": 136,
        "state": "payment",
        "name": "Nguyen 136 Thanh",
        "quantity": 272,
        "dateOrder": "18.06.2019",
        "total": 6392000,
        "level": 1
    },
    {
        "id": 137,
        "state": "payment",
        "name": "Nguyen 137 Thanh",
        "quantity": 274,
        "dateOrder": "18.06.2019",
        "total": 6439000,
        "level": 0
    },
    {
        "id": 138,
        "state": "payment",
        "name": "Nguyen 138 Thanh",
        "quantity": 276,
        "dateOrder": "18.06.2019",
        "total": 6486000,
        "level": 0
    },
    {
        "id": 139,
        "state": "payment",
        "name": "Nguyen 139 Thanh",
        "quantity": 278,
        "dateOrder": "18.06.2019",
        "total": 6533000,
        "level": 0
    },
    {
        "id": 140,
        "state": "payment",
        "name": "Nguyen 140 Thanh",
        "quantity": 280,
        "dateOrder": "18.06.2019",
        "total": 6580000,
        "level": 1
    },
    {
        "id": 141,
        "state": "payment",
        "name": "Nguyen 141 Thanh",
        "quantity": 282,
        "dateOrder": "18.06.2019",
        "total": 6627000,
        "level": 1
    },
    {
        "id": 142,
        "state": "payment",
        "name": "Nguyen 142 Thanh",
        "quantity": 284,
        "dateOrder": "18.06.2019",
        "total": 6674000,
        "level": 0
    },
    {
        "id": 143,
        "state": "payment",
        "name": "Nguyen 143 Thanh",
        "quantity": 286,
        "dateOrder": "18.06.2019",
        "total": 6721000,
        "level": 0
    },
    {
        "id": 144,
        "state": "payment",
        "name": "Nguyen 144 Thanh",
        "quantity": 288,
        "dateOrder": "18.06.2019",
        "total": 6768000,
        "level": 0
    },
    {
        "id": 145,
        "state": "payment",
        "name": "Nguyen 145 Thanh",
        "quantity": 290,
        "dateOrder": "18.06.2019",
        "total": 6815000,
        "level": 1
    },
    {
        "id": 146,
        "state": "payment",
        "name": "Nguyen 146 Thanh",
        "quantity": 292,
        "dateOrder": "18.06.2019",
        "total": 6862000,
        "level": 0
    },
    {
        "id": 147,
        "state": "payment",
        "name": "Nguyen 147 Thanh",
        "quantity": 294,
        "dateOrder": "18.06.2019",
        "total": 6909000,
        "level": 1
    },
    {
        "id": 148,
        "state": "payment",
        "name": "Nguyen 148 Thanh",
        "quantity": 296,
        "dateOrder": "18.06.2019",
        "total": 6956000,
        "level": 1
    },
    {
        "id": 149,
        "state": "payment",
        "name": "Nguyen 149 Thanh",
        "quantity": 298,
        "dateOrder": "18.06.2019",
        "total": 7003000,
        "level": 1
    },
    {
        "id": 150,
        "state": "payment",
        "name": "Nguyen 150 Thanh",
        "quantity": 300,
        "dateOrder": "18.06.2019",
        "total": 7050000,
        "level": 1
    },
    {
        "id": 151,
        "state": "payment",
        "name": "Nguyen 151 Thanh",
        "quantity": 302,
        "dateOrder": "18.06.2019",
        "total": 7097000,
        "level": 0
    },
    {
        "id": 152,
        "state": "payment",
        "name": "Nguyen 152 Thanh",
        "quantity": 304,
        "dateOrder": "18.06.2019",
        "total": 7144000,
        "level": 0
    },
    {
        "id": 153,
        "state": "payment",
        "name": "Nguyen 153 Thanh",
        "quantity": 306,
        "dateOrder": "18.06.2019",
        "total": 7191000,
        "level": 1
    },
    {
        "id": 154,
        "state": "payment",
        "name": "Nguyen 154 Thanh",
        "quantity": 308,
        "dateOrder": "18.06.2019",
        "total": 7238000,
        "level": 1
    },
    {
        "id": 155,
        "state": "payment",
        "name": "Nguyen 155 Thanh",
        "quantity": 310,
        "dateOrder": "18.06.2019",
        "total": 7285000,
        "level": 1
    },
    {
        "id": 156,
        "state": "payment",
        "name": "Nguyen 156 Thanh",
        "quantity": 312,
        "dateOrder": "18.06.2019",
        "total": 7332000,
        "level": 0
    },
    {
        "id": 157,
        "state": "payment",
        "name": "Nguyen 157 Thanh",
        "quantity": 314,
        "dateOrder": "18.06.2019",
        "total": 7379000,
        "level": 1
    },
    {
        "id": 158,
        "state": "payment",
        "name": "Nguyen 158 Thanh",
        "quantity": 316,
        "dateOrder": "18.06.2019",
        "total": 7426000,
        "level": 1
    },
    {
        "id": 159,
        "state": "payment",
        "name": "Nguyen 159 Thanh",
        "quantity": 318,
        "dateOrder": "18.06.2019",
        "total": 7473000,
        "level": 1
    },
    {
        "id": 160,
        "state": "payment",
        "name": "Nguyen 160 Thanh",
        "quantity": 320,
        "dateOrder": "18.06.2019",
        "total": 7520000,
        "level": 1
    },
    {
        "id": 161,
        "state": "payment",
        "name": "Nguyen 161 Thanh",
        "quantity": 322,
        "dateOrder": "18.06.2019",
        "total": 7567000,
        "level": 0
    },
    {
        "id": 162,
        "state": "payment",
        "name": "Nguyen 162 Thanh",
        "quantity": 324,
        "dateOrder": "18.06.2019",
        "total": 7614000,
        "level": 1
    },
    {
        "id": 163,
        "state": "payment",
        "name": "Nguyen 163 Thanh",
        "quantity": 326,
        "dateOrder": "18.06.2019",
        "total": 7661000,
        "level": 1
    },
    {
        "id": 164,
        "state": "payment",
        "name": "Nguyen 164 Thanh",
        "quantity": 328,
        "dateOrder": "18.06.2019",
        "total": 7708000,
        "level": 1
    },
    {
        "id": 165,
        "state": "payment",
        "name": "Nguyen 165 Thanh",
        "quantity": 330,
        "dateOrder": "18.06.2019",
        "total": 7755000,
        "level": 0
    },
    {
        "id": 166,
        "state": "payment",
        "name": "Nguyen 166 Thanh",
        "quantity": 332,
        "dateOrder": "18.06.2019",
        "total": 7802000,
        "level": 1
    },
    {
        "id": 167,
        "state": "payment",
        "name": "Nguyen 167 Thanh",
        "quantity": 334,
        "dateOrder": "18.06.2019",
        "total": 7849000,
        "level": 1
    },
    {
        "id": 168,
        "state": "payment",
        "name": "Nguyen 168 Thanh",
        "quantity": 336,
        "dateOrder": "18.06.2019",
        "total": 7896000,
        "level": 0
    },
    {
        "id": 169,
        "state": "payment",
        "name": "Nguyen 169 Thanh",
        "quantity": 338,
        "dateOrder": "18.06.2019",
        "total": 7943000,
        "level": 0
    },
    {
        "id": 170,
        "state": "payment",
        "name": "Nguyen 170 Thanh",
        "quantity": 340,
        "dateOrder": "18.06.2019",
        "total": 7990000,
        "level": 1
    },
    {
        "id": 171,
        "state": "payment",
        "name": "Nguyen 171 Thanh",
        "quantity": 342,
        "dateOrder": "18.06.2019",
        "total": 8037000,
        "level": 0
    },
    {
        "id": 172,
        "state": "payment",
        "name": "Nguyen 172 Thanh",
        "quantity": 344,
        "dateOrder": "18.06.2019",
        "total": 8084000,
        "level": 1
    },
    {
        "id": 173,
        "state": "payment",
        "name": "Nguyen 173 Thanh",
        "quantity": 346,
        "dateOrder": "18.06.2019",
        "total": 8131000,
        "level": 0
    },
    {
        "id": 174,
        "state": "payment",
        "name": "Nguyen 174 Thanh",
        "quantity": 348,
        "dateOrder": "18.06.2019",
        "total": 8178000,
        "level": 0
    },
    {
        "id": 175,
        "state": "payment",
        "name": "Nguyen 175 Thanh",
        "quantity": 350,
        "dateOrder": "18.06.2019",
        "total": 8225000,
        "level": 1
    },
    {
        "id": 176,
        "state": "payment",
        "name": "Nguyen 176 Thanh",
        "quantity": 352,
        "dateOrder": "18.06.2019",
        "total": 8272000,
        "level": 0
    },
    {
        "id": 177,
        "state": "payment",
        "name": "Nguyen 177 Thanh",
        "quantity": 354,
        "dateOrder": "18.06.2019",
        "total": 8319000,
        "level": 0
    },
    {
        "id": 178,
        "state": "payment",
        "name": "Nguyen 178 Thanh",
        "quantity": 356,
        "dateOrder": "18.06.2019",
        "total": 8366000,
        "level": 1
    },
    {
        "id": 179,
        "state": "payment",
        "name": "Nguyen 179 Thanh",
        "quantity": 358,
        "dateOrder": "18.06.2019",
        "total": 8413000,
        "level": 0
    },
    {
        "id": 180,
        "state": "payment",
        "name": "Nguyen 180 Thanh",
        "quantity": 360,
        "dateOrder": "18.06.2019",
        "total": 8460000,
        "level": 0
    },
    {
        "id": 181,
        "state": "payment",
        "name": "Nguyen 181 Thanh",
        "quantity": 362,
        "dateOrder": "18.06.2019",
        "total": 8507000,
        "level": 0
    },
    {
        "id": 182,
        "state": "payment",
        "name": "Nguyen 182 Thanh",
        "quantity": 364,
        "dateOrder": "18.06.2019",
        "total": 8554000,
        "level": 1
    },
    {
        "id": 183,
        "state": "payment",
        "name": "Nguyen 183 Thanh",
        "quantity": 366,
        "dateOrder": "18.06.2019",
        "total": 8601000,
        "level": 0
    },
    {
        "id": 184,
        "state": "payment",
        "name": "Nguyen 184 Thanh",
        "quantity": 368,
        "dateOrder": "18.06.2019",
        "total": 8648000,
        "level": 1
    },
    {
        "id": 185,
        "state": "payment",
        "name": "Nguyen 185 Thanh",
        "quantity": 370,
        "dateOrder": "18.06.2019",
        "total": 8695000,
        "level": 0
    },
    {
        "id": 186,
        "state": "payment",
        "name": "Nguyen 186 Thanh",
        "quantity": 372,
        "dateOrder": "18.06.2019",
        "total": 8742000,
        "level": 0
    },
    {
        "id": 187,
        "state": "payment",
        "name": "Nguyen 187 Thanh",
        "quantity": 374,
        "dateOrder": "18.06.2019",
        "total": 8789000,
        "level": 0
    },
    {
        "id": 188,
        "state": "payment",
        "name": "Nguyen 188 Thanh",
        "quantity": 376,
        "dateOrder": "18.06.2019",
        "total": 8836000,
        "level": 1
    },
    {
        "id": 189,
        "state": "payment",
        "name": "Nguyen 189 Thanh",
        "quantity": 378,
        "dateOrder": "18.06.2019",
        "total": 8883000,
        "level": 0
    },
    {
        "id": 190,
        "state": "payment",
        "name": "Nguyen 190 Thanh",
        "quantity": 380,
        "dateOrder": "18.06.2019",
        "total": 8930000,
        "level": 0
    },
    {
        "id": 191,
        "state": "payment",
        "name": "Nguyen 191 Thanh",
        "quantity": 382,
        "dateOrder": "18.06.2019",
        "total": 8977000,
        "level": 1
    },
    {
        "id": 192,
        "state": "payment",
        "name": "Nguyen 192 Thanh",
        "quantity": 384,
        "dateOrder": "18.06.2019",
        "total": 9024000,
        "level": 1
    },
    {
        "id": 193,
        "state": "payment",
        "name": "Nguyen 193 Thanh",
        "quantity": 386,
        "dateOrder": "18.06.2019",
        "total": 9071000,
        "level": 1
    },
    {
        "id": 194,
        "state": "payment",
        "name": "Nguyen 194 Thanh",
        "quantity": 388,
        "dateOrder": "18.06.2019",
        "total": 9118000,
        "level": 1
    },
    {
        "id": 195,
        "state": "payment",
        "name": "Nguyen 195 Thanh",
        "quantity": 390,
        "dateOrder": "18.06.2019",
        "total": 9165000,
        "level": 1
    },
    {
        "id": 196,
        "state": "payment",
        "name": "Nguyen 196 Thanh",
        "quantity": 392,
        "dateOrder": "18.06.2019",
        "total": 9212000,
        "level": 0
    },
    {
        "id": 197,
        "state": "payment",
        "name": "Nguyen 197 Thanh",
        "quantity": 394,
        "dateOrder": "18.06.2019",
        "total": 9259000,
        "level": 1
    },
    {
        "id": 198,
        "state": "payment",
        "name": "Nguyen 198 Thanh",
        "quantity": 396,
        "dateOrder": "18.06.2019",
        "total": 9306000,
        "level": 0
    },
    {
        "id": 199,
        "state": "payment",
        "name": "Nguyen 199 Thanh",
        "quantity": 398,
        "dateOrder": "18.06.2019",
        "total": 9353000,
        "level": 0
    }
]